Workbook

Sheet Valuation
B2: Basic Information from Dune Analytics | H2: Valuation Summary of Nov/22 | T2: Appendix
B4: Month | C4: Total transaction fees | D4: Total transactions | E4: Active Account | F4: GNO Price | H4: Target PF ratio of Comparables in Nob/22 | I4: ='PF Ratio Comparables'!C24 -> 177.938 | T4: Year | U4: Apple card users | V4: Growth rate
B5: 44136 | C5: 544 | D5: 1100799 | E5: 12744 | F5: 41 | T5: 2019 | U5: 1600000
B6: 44166 | C6: 559 | D6: 1089356 | E6: 9654 | F6: 62 | H6: Last twleve month active users | I6: =AVERAGE(E5:E29) -> 105704.68 | T6: 2020 | U6: 3100000 | V6: =(U6/U5)-1 -> 0.9375
B7: 44197 | C7: 2197 | D7: 3185226 | E7: 12743 | F7: 75 | T7: 2021 | U7: 6400000 | V7: =(U7/U6)-1 -> 1.0645161
B8: 44228 | C8: 42558 | D8: 3011489 | E8: 40418 | F8: 112 | H8: Fees from Last Twelve Months | I8: =SUM(C17:C29) -> 1785105 | T8: 2022 | U8: 7700000 | V8: =(U8/U7)-1 -> 0.203125
B9: 44256 | C9: 129119 | D9: 4848266 | E9: 95853 | F9: 124 | H9: Fees from Last Twenty-Four Months/2 | I9: =SUM(C5:C29)/2 -> 2197384 | J9: *Assumption for 2021 fees | U9: Geo.Average | V9: =((1+V6)*(1+V7)*(1+V8))^(1/3)-1 -> 0.68832835
B10: 44287 | C10: 142163 | D10: 4215811 | E10: 47192 | F10: 170
B11: 44317 | C11: 533899 | D11: 7513673 | E11: 37597 | F11: 228 | H11: Average revenue per user (ARPU) | I11: =I9/I6 -> 20.787954
B12: 44348 | C12: 439345 | D12: 6891864 | E12: 501015 | F12: 187 | T12: VISA | U12: Revenue | V12: Growth
B13: 44378 | C13: 205642 | D13: 6622998 | E13: 320453 | F13: 162 | T13: 2012 | U13: 10421 | V13: =(U13-U14)/U14 -> 0.13419678
B14: 44409 | C14: 264627 | D14: 9090866 | E14: 471760 | F14: 193 | H14: Circulating supply | I14: 2579589 | T14: 2011 | U14: 9188 | V14: =(U14-U15)/U15 -> 0.13924365
B15: 44440 | C15: 566112 | D15: 7882158 | E15: 188412 | F15: 281 | H15: Total supply | I15: 3000000 | T15: 2010 | U15: 8065
B16: 44470 | C16: 282898 | D16: 7810838 | E16: 134708 | F16: 273
B17: 44501 | C17: 323745 | D17: 5603630 | E17: 100471 | F17: 449
B18: 44531 | C18: 388017 | D18: 6938242 | E18: 97704 | F18: 461 | H18: Market Cap (12) | I18: =I8*$I$4 -> 3.1763801e+08 | T18: MasterCard
B19: 44562 | C19: 413798 | D19: 5761675 | E19: 73811 | F19: 532 | H19: Market Cap (24/2) | I19: =I9*$I$4 -> 3.9099811e+08 | T19: 2012 | U19: 7391 | V19: =(U19-U20)/U20 -> 0.10083408
B20: 44593 | C20: 160551 | D20: 5047650 | E20: 76620 | F20: 294 | T20: 2011 | U20: 6714 | V20: =(U20-U21)/U21 -> 0.21213215
B21: 44621 | C21: 164057 | D21: 4455106 | E21: 80816 | F21: 354 | H21: 44887 | I21: Target price | T21: 2010 | U21: 5539
B22: 44652 | C22: 131290 | D22: 3871965 | E22: 54442 | F22: 421 | H22: Price of the token(12) | I22: =I18/$I$14 -> 123.13512
B23: 44682 | C23: 189690 | D23: 6164423 | E23: 51050 | F23: 309 | H23: Price of the token(24/2) | I23: =I19/$I$14 -> 151.5738 | J23: The thepry price of today
B24: 44713 | C24: 3949 | D24: 2218339 | E24: 35990 | F24: 204 | H24: Diluted Price of GNO(12) | I24: =I18/$I$15 -> 105.87934
B25: 44743 | C25: 1738 | D25: 1827330 | E25: 27776 | F25: 109 | H25: Diluted Price of GNO(24/2) | I25: =I19/$I$15 -> 130.3327
B26: 44774 | C26: 2801 | D26: 2133566 | E26: 27355 | F26: 160
B27: 44805 | C27: 2709 | D27: 2431087 | E27: 44407 | F27: 155
B28: 44835 | C28: 1327 | D28: 2974297 | E28: 78184 | F28: 119
B29: 44866 | C29: 1433 | D29: 1837668 | E29: 21442 | F29: 127
E32: Total Transactions last 90 days
E33: 7845282
E34: Active accounts in last 90 days
E35: 127428
E36: Transaction fees last 90 days
E37: 6127
B38: Link | E38: Today price | F38: 79
B42: Active Users projection | E42: Revenue
B44: ** Assumption for the card issueance from Oly project has the same growth rate as Apple Card
B45: Year | C45: User growth rate | D45: User | E45: Gnosis Revenue | F45: ARPU | G45: Revenue Growth Rate
B46: N+1 (2023) | C46: =Valuation!V6 -> 0.9375 | D46: =I6*(1+C46) -> 204802.82 | E46: 2913295.9 | F46: 14.224882 | G46: 0.32580193
B47: N+2 (2024) | C47: =Valuation!V7 -> 1.0645161 | D47: =D46*(1+C47) -> 422818.72 | E47: 3735458.6 | F47: 8.8346575 | G47: 0.28221047
B48: N+3 (2025) | C48: =Valuation!V8 -> 0.203125 | D48: =D47*(1+C48) -> 508703.77 | E48: 5825741.4 | F48: 11.452129 | G48: 0.55957864
G54: `
B65: Assumtion for PF ratio and Revenue (Transaction fee) growth rate
B67: *** Revenue Growth rate and PF ratio Growth rate assume as the geometric average of Bolck (Square) and PayPal (Venmo)
B68: **** Use the time frame from 2018 to 2020. (2018 Jack Dorsey launch bitcoin trading and plan for bitcoin payment)
B70: Block History PS ratio | C70: PS Ratio | D70: Growth Rate | E70: Revenue | F70: Revenue Growth Rate
B71: 2017 | C71: 5.17 | E71: 2214
B72: 2018 | C72: 13.77 | D72: =(C72/C71)-1 -> 1.6634429 | E72: 3298 | F72: =(E72/E71)-1 -> 0.48961156
B73: 2019 | C73: 6.15 | D73: =(C73/C72)-1 -> -0.55337691 | E73: 4714 | F73: =(E73/E72)-1 -> 0.42935112
B74: 2020 | C74: 9.8 | D74: =(C74/C73)-1 -> 0.59349593 | E74: 9498 | F74: =(E74/E73)-1 -> 1.0148494
C76: Geo.Average | D76: =((1+D72)*(1+D73)*(1+D74))^(1/3)-1 -> 0.2375949 | F76: =((1+F72)*(1+F73)*(1+F74))^(1/3)-1 -> 0.62486836
B77: Paypal History PS ratio
B78: 2016 | C78: 4.39 | E78: 10842
B79: 2017 | C79: 6.39 | D79: =(C79/C78)-1 -> 0.45558087 | E79: 13094 | F79: =(E79/E78)-1 -> 0.20771075
B80: 2018 | C80: 7.37 | D80: =(C80/C79)-1 -> 0.15336463 | E80: 15451 | F80: =(E80/E79)-1 -> 0.18000611
B81: 2019 | C81: 8.37 | D81: =(C81/C80)-1 -> 0.13568521 | E81: 17772 | F81: =(E81/E80)-1 -> 0.15021681
B82: 2020 | C82: 12.95 | D82: =(C82/C81)-1 -> 0.54719235 | E82: 21454 | F82: =(E82/E81)-1 -> 0.20717983
C83: Geo.Average | D83: =((1+D81)*(1+D82)*(1+D80))^(1/3)-1 -> 0.26548297 | F83: =((1+F80)*(1+F81)*(1+F82))^(1/3)-1 -> 0.17890456
B85: AVERAGE | D85: PS Growth rate | F85: Revenue Growth Rate
B86: 2017
B87: 2018 | D87: =((1+D72)*(1+D80))^(1/2)-1 -> 0.75268962 | F87: =((1+F72)*(1+F80))^(1/2)-1 -> 0.32580193
B88: 2019 | D88: =((1+D73)*(1+D81))^(1/2)-1 -> -0.28780393 | F88: =((1+F73)*(1+F81))^(1/2)-1 -> 0.28221047
B89: 2020 | D89: =((1+D74)*(1+D82))^(1/2)-1 -> 0.57017347 | F89: =((1+F74)*(1+F82))^(1/2)-1 -> 0.55957864
C90: Geo.Average | D90: =((1+D88)*(1+D89)*(1+D87))^(1/3)-1 -> 0.25146125 | F90: =((1+F88)*(1+F89)*(1+F87))^(1/3)-1 -> 0.38403928
B94: Target price of GNO in 2025
B96: ***** Assume fee = Revenue in Gnosis Chain, but still use PF ratio, because of the PS ratio of comparables (Polygon, Fantom) are not reasonable
B97: Year | C97: Gnosis PF ratio | E97: Gnosis Revenue | G97: ARPU
B98: 2023 | C98: =$I$4*(1+D87) -> 311.87008 | E98: =I9*(1+F87) -> 2913295.9 | G98: =E98/D46 -> 14.224882
B99: 2024 | C99: =C98*(1+D88) -> 222.11265 | E99: =E98*(1+F88) -> 3735458.6 | G99: =E99/D47 -> 8.8346575
B100: 2025 | C100: =C99*(1+D89) -> 348.75539 | E100: =E99*(1+F89) -> 5825741.4 | G100: =E100/D48 -> 11.452129
B102: Market Cap in 2025 | C102: =E100*C100 -> 2.0317587e+09
B103: Price | C103: =C102/3000000 -> 677.2529
B110: Defi Ecosystem
B111: Panel

Sheet PF Ratio Comparables
B2: PF Ratio comparables
B6: Selected
B7: Layer 1 | C7: Circulating Maket Cap | D7: Fully diluted Market Cap | E7: PS-fully diluted | F7: PS circulating | G7: PF Fully diluted | H7: PF circulating | I7: Annualized Fee | J7: Revenue past 365 days | K7: Revenue annualized (Onchain)
B8: Ethereum | H8: 114.8 | J8: 5100000000
B9: BSC | C9: 42010000000 | D9: 51460000000 | E9: 1896 | G9: 189.5 | H9: 154.8 | I9: 287450000 | J9: 52300000 | K9: 28720000
B10: Fantom | C10: 435500000 | D10: 544130000 | E10: 525 | G10: 157 | I10: 3710000 | J10: 7900000 | K10: 1100000
B12: Layer 2
B13: Optimism | C13: 177930000 | D13: 3560000000 | E13: 918 | G13: 204 | I13: 19520000 | J13: 5800000 | K13: 4350000
B14: Polygon | C14: 6980000000 | D14: 7870000000 | G14: 224.39 | I14: 39140000 | J14: 4600000 | K14: 15600000
B16: Gnosis | C16: 204992231 | D16: 238401037 | H16: =C16/I16 -> 114.83483 | I16: =Valuation!I8 -> 1785105 | K16: 15100000 | L16: ***Not reliable source
B17: Not Selected
B18: Solana | C18: 4280000000 | F18: 569 | H18: 284.81 | I18: 16440000 | K18: 8220000
B19: Polkadot | C19: 6090000000 | F19: 16294 | H19: 13035 | I19: 495555 | K19: 396440
B20: Avalanche | C20: 3570000000 | D20: 8550000000 | E20: 1257 | G20: 1257 | I20: 7380000 | K20: 7380000
B21: Tron
B22: Arbitrum | I22: 12710000 | J22: 7600000 | K22: 3260000
B24: Average | C24: =AVERAGE(H8,G9,G14,G13,G10) -> 177.938
B26: *P/F ratio: fully diluted market cap / annualized fees.
B27: ** Source: Token Terminal, CoinGecko
B33: Binance revenue
B34: 2020 | C34: 5.5B
B35: 2021 | C35: 20B

Sheet 3 Factors regression
B2: Three factors regression
B4: Regression Statistics
B5: Multiple R | C5: 0.67562504
B6: R Square | C6: 0.4564692 | D6: *The measure of how much change of the price is driven by other variables, Transaction fee, Total transactions and active accounts
B7: Adjusted R Square | C7: 0.37882194 | D7: **46% of the variation in price, good correlation
B8: Standard Error | C8: 105.69737
B9: Observations | C9: 25
B11: ANOVA
C12: df | D12: SS | E12: MS | F12: F | G12: Significance F
B13: Regression | C13: 3 | D13: 197031.2 | E13: 65677.068 | F13: 5.8787549 | G13: 0.0044530647 | H13: <0.05 | I13: ***Strong correlation
B14: Residual | C14: 21 | D14: 234610.64 | E14: 11171.935
B15: Total | C15: 24 | D15: 431641.84
C17: Coefficients | D17: Standard Error | E17: t Stat | F17: P-value | G17: Lower 95% | H17: Upper 95% | I17: Lower 95.0% | J17: Upper 95.0%
B18: Intercept | C18: 111.44255 | D18: 59.369034 | E18: 1.8771157 | F18: 0.074465342 | G18: -12.022118 | H18: 234.90721 | I18: -12.022118 | J18: 234.90721
B19: Total transaction fees | C19: 0.0003639193 | D19: 0.00024005685 | E19: 1.5159713 | F19: 0.14443566 | G19: -0.00013530624 | H19: 0.00086314484 | I19: -0.00013530624 | J19: 0.00086314484
B20: Total transactions | C20: 2.0472692e-05 | D20: 2.1503701e-05 | E20: 0.95205438 | F20: 0.35189975 | G20: -2.4246701e-05 | H20: 6.5192086e-05 | I20: -2.4246701e-05 | J20: 6.5192086e-05
B21: Active Account | C21: -0.00042689035 | D21: 0.00022262231 | E21: -1.9175542 | F21: 0.068870563 | G21: -0.00088985877 | H21: 3.6078083e-05 | I21: -0.00088985877 | J21: 3.6078083e-05
F22: >0.05 | G22: ****These three factors do not have an real effect on the price
B24: One Factor regression
B26: Regression Statistics
B27: Multiple R | C27: 0.60074943
B28: R Square | C28: 0.36089988 | D28: *The measure of how much change of the price is driven by other variable, Transaction fee
B29: Adjusted R Square | C29: 0.33311292 | D29: **36% of the variation in price, good correlation
B30: Standard Error | C30: 109.51719
B31: Observations | C31: 25
B33: ANOVA
C34: df | D34: SS | E34: MS | F34: F | G34: Significance F
B35: Regression | C35: 1 | D35: 155779.49 | E35: 155779.49 | F35: 12.988102 | G35: 0.0014956851 | H35: <0.05 | I35: ***Strong correlation
B36: Residual | C36: 23 | D36: 275862.35 | E36: 11994.015
B37: Total | C37: 24 | D37: 431641.84
C39: Coefficients | D39: Standard Error | E39: t Stat | F39: P-value | G39: Lower 95% | H39: Upper 95% | I39: Lower 95.0% | J39: Upper 95.0%
B40: Intercept | C40: 145.99795 | D40: 30.808689 | E40: 4.7388564 | F40: 8.9249564e-05 | G40: 82.265325 | H40: 209.73058 | I40: 82.265325 | J40: 209.73058
B41: Total transaction fees | C41: 0.00044417615 | D41: 0.00012324872 | E41: 3.6039009 | F41: 0.0014956851 | G41: 0.00018921676 | H41: 0.00069913555 | I41: 0.00018921676 | J41: 0.00069913555
F42: <0.05 | G42: The Transaction fee coefficient have an real effect on the price

Sheet Token terminal
A1: Token Terminal Master Excel SAMPLE DATA
B2: Price & Market cap | Q2: Total Value Locked (TVL) | AA2: GMV | AB2: Total revenue | AJ2: Protocol revenue | AR2: Price to sales (P/S) ratio | BB2: Twitter
A3: Project | B3: Symbol | C3: Launch date | D3: Category tags | E3: Price latest | F3: 24h change | G3: 7d change | H3: 30d change | I3: 90d change | J3: 180d change | K3: ATH | L3: ATL | M3: Volume 24h | N3: Circulating market cap latest | O3: Fully-diluted market cap latest | P3: Volume / MC ratio | Q3: TVL latest | R3: 24h change | S3: 7d change | T3: 30d change | U3: 90d change | V3: 180d change | W3: 7d avg. TVL | X3: 30d avg. TVL | Y3: 90d avg. TVL | Z3: 180d avg. TVL | AA3: Annualized GMV | AB3: 7d total revenue | AC3: 7d change | AD3: 30d total revenue | AE3: 30d change | AF3: 90d total revenue | AG3: 90d change | AH3: 180d total revenue | AI3: 180d change | AJ3: 7d protocol revenue | AK3: 7d change | AL3: 30d protocol revenue | AM3: 30d change | AN3: 90d protocol revenue | AO3: 90d change | AP3: 180d protocol revenue | AQ3: 180d change | AR3: P/S ratio latest | AS3: 24h change | AT3: 7d change | AU3: 30d change | AV3: 90d change | AW3: 180d change | AX3: 7d avg. P/S ratio | AY3: 30d avg. P/S ratio | AZ3: 90d avg. P/S ratio | BA3: 180d avg. P/S ratio | BB3: Twitter followers latest
A4: 0x | B4: ZRX | C4: 2017-08-15 | D4: DeFi Exchange | E4: 0.907061 | F4: 0.10703848 | G4: -0.40235191 | H4: -0.35046609 | I4: -0.4197824 | J4: 0.99653022 | K4: 2.5 | L4: 0.120667 | M4: 2.7001483e+08 | N4: 7.6501998e+08 | O4: 907061000 | P4: 0.30335273 | AA4: 1.6301887e+11 | AB4: 304258.26 | AC4: 0.096827208 | AD4: 1127205.2 | AE4: 1.2395466 | AF4: 2216957.2 | AG4: 0.58523423 | AH4: 3334105.2 | AI4: 23.478474 | AJ4: 304258.26 | AK4: 0.096827208 | AL4: 1127205.2 | AM4: 1.2395466 | AN4: 2216957.2 | AO4: 0.58523423 | AP4: 3334105.2 | AQ4: 23.478474 | AR4: 68.344306 | AS4: -0.097799426 | AT4: -0.31293775 | AU4: -0.66483615 | AV4: -0.70743155 | AW4: -0.7405759 | AX4: 99.473236 | AY4: 203.91312 | AZ4: 233.60108 | BA4: 263.44625 | BB4: 216397
A5: 88mph | B5: MPH | C5: 2019-10-10 | D5: DeFi Lending | E5: 46.97 | F5: 0.091601023 | G5: -0.5608729 | H5: -0.56405281 | I5: -0.56777604 | J5: 0.062370718 | K5: 236.5 | L5: 20.21 | M5: 1027323.9 | N5: 17269063 | O5: 18583868 | P5: 0.032602242 | Q5: 36197691 | R5: -0.033558483 | S5: -0.11415359 | T5: -0.17391465 | U5: 0.011792279 | V5: 0.58452993 | W5: 40862265 | X5: 43818343 | Y5: 35775813 | Z5: 22844435 | BB5: 11284
A6: Aave | B6: AAVE | C6: 2017-11-25 | D6: DeFi Lending | E6: 331.88 | F6: 0.15937335 | G6: -0.3963676 | H6: 0.0044495004 | I6: -0.1296904 | J6: 4.1241903 | K6: 661.69 | L6: 26.02 | M6: 1.4181195e+09 | N6: 4.1994751e+09 | O6: 5310080000 | P6: 0.18857959 | Q6: 1.050661e+10 | R6: -0.051021408 | S6: -0.15439516 | T6: -0.034643738 | U6: 0.42553116 | V6: 1.0924891 | W6: 1.2424965e+10 | X6: 1.0883661e+10 | Y6: 7.3703125e+09 | Z6: 5.0211062e+09 | AA6: 5.5005466e+09 | AB6: 8129873.6 | AC6: 0.15120587 | AD6: 32423093 | AE6: 1.4837325 | AF6: 55098785 | AG6: 2.3932115 | AH6: 70425502 | AI6: 29.709802 | AJ6: 760441.98 | AK6: 0.18732081 | AL6: 2986505.5 | AM6: 2.5899863 | AN6: 4425182.8 | AO6: 6.2983902 | AP6: 4994487.5 | AQ6: 101.00346 | AR6: 13.909626 | AS6: -0.09091701 | AT6: -0.34089114 | AU6: -0.56422243 | AV6: -0.66893696 | AW6: -0.75651965 | AX6: 21.103685 | AY6: 31.919095 | AZ6: 42.015037 | BA6: 57.128331 | BB6: 214534
A7: Alchemix Finance | B7: ALCX | C7: 2021-01-22 | D7: Asset Management DeFi Lending Stablecoin | E7: 743.64 | F7: 0.021960944 | G7: -0.42644238 | H7: -0.44088072 | K7: 2066.2 | L7: 279.54 | M7: 13907026 | N7: 2.0807814e+08 | O7: 1.7795751e+09 | P7: 0.0066225113 | Q7: 1.071144e+09 | R7: -0.026839883 | S7: -0.1234801 | T7: -0.19994347 | U7: -0.033765659 | V7: -0.033765659 | W7: 1.2220418e+09 | X7: 1.3388354e+09 | Y7: 1.1085758e+09 | Z7: 1.1085758e+09 | BB7: 29238
A8: Autofarm | B8: AUTO | C8: 2020-04-23 | D8: Asset Management DeFi | E8: 1299.56 | F8: 0.1035277 | G8: -0.49749179 | H8: -0.42671596 | I8: -0.8422835 | M8: 8204246.8 | N8: 32857026 | O8: 103964800 | P8: 0.11919149 | Q8: 9.5969067e+08 | R8: -0.06254338 | S8: -0.22997534 | T8: -0.31602927 | U8: -0.33943608 | V8: -0.34102515 | W8: 1.2463116e+09 | X8: 1.4031166e+09 | Y8: 1.4528354e+09 | Z8: 1.4563388e+09 | BB8: 63514
A9: Balancer | B9: BAL | C9: 2020-06-20 | D9: DeFi Exchange | E9: 28.34 | F9: 0.078847702 | G9: -0.4517283 | H9: -0.41477158 | I9: -0.25351982 | J9: 0.84923798 | K9: 74.45 | L9: 6.65 | M9: 79185559 | N9: 3.0481911e+08 | O9: 2834000000 | P9: 0.017410493 | Q9: 2.4074436e+09 | R9: -0.0446621 | S9: -0.16877407 | T9: -0.22178452 | U9: -0.027803483 | V9: 0.43615639 | W9: 2.8962566e+09 | X9: 3.0935436e+09 | Y9: 2.4762931e+09 | Z9: 1.6763102e+09 | AA9: 3.39778e+10 | AB9: 2815666.8 | AC9: 0.12064135 | AD9: 9429549.5 | AE9: 0.72456298 | AF9: 19105441 | AG9: 0.66583765 | AH9: 30823906 | AI9: 4.1975352 | AR9: 25.525704 | AS9: -0.10088343 | AT9: -0.35836867 | AU9: -0.6197036 | AV9: -0.68247934 | AW9: -0.62224981 | AX9: 39.782509 | AY9: 67.120551 | AZ9: 80.390687 | BA9: 67.572975 | BB9: 82113
A10: Bancor | B10: BNT | C10: 2017-09-21 | D10: DeFi Exchange | E10: 4.16 | F10: 0.10065099 | G10: -0.36084167 | H10: -0.31758125 | I10: -0.29637248 | J10: 2.810484 | K10: 10.72 | L10: 0.120935 | M10: 4.617146e+08 | N10: 8.0688112e+08 | O10: 8.1003449e+08 | P10: 0.40973323 | Q10: 1.3519008e+09 | R10: -0.071599999 | S10: -0.22604298 | T10: -0.31416148 | U10: -0.20223554 | V10: 0.40424395 | W10: 1.7467389e+09 | X10: 1.9711649e+09 | Y10: 1.6946115e+09 | Z10: 9.6272503e+08 | AA10: 5.2864605e+10 | AB10: 4284116 | AC10: 0.093513258 | AD10: 13469612 | AE10: 0.56504614 | AF10: 29467903 | AG10: 5.473106 | AH10: 32450161 | AI10: 85.727416 | AJ10: 2142058 | AK10: 0.093513258 | AL10: 6734805.8 | AM10: 0.56504614 | AN10: 14733951 | AO10: 5.473106 | AP10: 16225081 | AQ10: 85.727416 | AR10: 5.1076046 | AS10: -0.0092971274 | AT10: -0.2604826 | AU10: -0.50460389 | AV10: -0.69619694 | AW10: -0.85371244 | AX10: 6.9066727 | AY10: 10.310143 | AZ10: 16.812222 | BA10: 34.914826 | BB10: 118727
A11: Barnbridge | B11: BOND | C11: 2020-04-22 | D11: Asset Management DeFi | E11: 24.72 | F11: -0.20992017 | G11: -0.43226547 | H11: -0.40568554 | I11: -0.58194251 | J11: -0.073400313 | K11: 185.69 | L11: 14.22 | M11: 2963860.4 | N11: 65620697 | O11: 247200000 | P11: 0.009134637 | Q11: 83753683 | R11: -0.0030999202 | S11: -0.036732465 | T11: 0.22466328 | U11: -0.66465212 | V11: -0.69396919 | W11: 86947478 | X11: 68389152 | Y11: 2.4975164e+08 | Z11: 2.7367729e+08 | BB11: 17866
A12: Basket DAO | B12: BASK | C12: 2021-03-23 | D12: Asset Management DeFi | Q12: 27543302 | R12: -0.12622276 | S12: -0.30633074 | T12: -0.60572204 | U12: -0.57734542 | V12: -0.57734542 | W12: 39706678 | X12: 69857574 | Y12: 65167405 | Z12: 65167405 | BB12: 2943
A13: Binance Chain | B13: BNB | C13: 2020-09-10 | D13: Blockchain | E13: 278.74 | F13: -0.026440458 | G13: -0.50567384 | H13: -0.47186382 | I13: 0.038555558 | J13: 7.2613755 | K13: 686.31 | L13: 0.0398177 | M13: 7.987128e+09 | N13: 4.2952964e+10 | O13: 4.753455e+10 | P13: 0.1176802 | AA13: 7.7034172e+10 | AC13: -0.33448764 | AD13: 2324172.9 | AE13: -0.29150011 | AF13: 12416243 | AG13: 0.010772639 | AH13: 17036303 | AI13: 0.16155919 | AR13: 1737.0398 | AS13: -0.1222384 | AT13: -0.12094467 | AU13: -0.15752129 | AV13: 0.27553938 | AW13: 0.67863989 | AX13: 1976.0301 | AY13: 2061.8204 | AZ13: 1361.8081 | BA13: 1034.79 | BB13: 639699
A14: Bitcoin | B14: BTC | C14: 2009-01-03 | D14: Blockchain | E14: 35826 | F14: -0.020315104 | G14: -0.23095523 | H14: -0.30015212 | I14: -0.34156522 | J14: 0.87653954 | K14: 64805 | L14: 67.81 | M14: 9.0511677e+10 | N14: 6.7043571e+11 | O14: 752346000000 | P14: 0.12505512 | AA14: 5.2050552e+12 | AB14: 30220814 | AC14: -0.26208377 | AD14: 1.7310822e+08 | AE14: -0.23984877 | AF14: 5.660553e+08 | AG14: -0.010482923 | AH14: 8.9870784e+08 | AI14: 1.646859 | AR14: 369.121 | AS14: 0.11937235 | AT14: 0.1748181 | AU14: 0.081324338 | AV14: -0.15227132 | AW14: -0.26647906 | AX14: 314.19417 | AY14: 341.36011 | AZ14: 435.42351 | BA14: 503.21808 | BB14: 2503911
A15: Centrifuge | B15: CFG | C15: 2020-05-20 | D15: DeFi Lending | AA15: 11280270 | AB15: 26047.301 | AC15: 0.13026086 | AD15: 84219.088 | AE15: 0.7495135 | AF15: 160756.98 | AG15: 3.7402801 | AH15: 190647.54 | AI15: 35.628085 | BB15: 19681
A16: Compound | B16: COMP | C16: 2018-09-27 | D16: DeFi Lending | E16: 383.88 | F16: 0.13965243 | G16: -0.44477675 | H16: -0.35507702 | I16: -0.041724773 | J16: 2.0579599 | K16: 910.54 | L16: 61.32 | M16: 3.0418952e+08 | N16: 1.9834605e+09 | O16: 3838800000 | P16: 0.085001754 | Q16: 7.3957384e+09 | R16: -0.02809021 | S16: -0.1527907 | T16: -0.22740345 | U16: -0.082086949 | V16: 0.36961416 | W16: 8.7295293e+09 | X16: 9.5725749e+09 | Y16: 8.057123e+09 | Z16: 5.39987e+09 | AA16: 7.5880219e+09 | AB16: 9198751.5 | AC16: -0.085824714 | AD16: 38924625 | AE16: -0.24615238 | AF16: 1.2223594e+08 | AG16: 0.23057409 | AH16: 1.7633186e+08 | AI16: 5.2587992 | AJ16: 1025213.4 | AK16: -0.078288206 | AL16: 4347950.9 | AM16: -0.22761007 | AN16: 13927400 | AO16: 0.1648472 | AP16: 20080253 | AQ16: 8.9576079 | AR16: 8.3760619 | AS16: -0.086087225 | AT16: -0.2739373 | AU16: -0.34493364 | AV16: -0.22657038 | AW16: -0.35017073 | AX16: 11.536279 | AY16: 12.786585 | AZ16: 10.829766 | BA16: 12.889635 | BB16: 142846
A17: Cream | B17: CREAM | C17: 2020-09-29 | D17: DeFi Lending | E17: 110.63 | F17: 0.14557652 | G17: -0.15519141 | H17: 0.1930851 | I17: -0.29059727 | J17: 1.4981227 | K17: 374.1 | L17: 9.36 | M17: 6207926.2 | N17: 81876577 | O17: 3.2354263e+08 | P17: 0.01938129 | Q17: 2.1712744e+08 | R17: -0.089128991 | S17: -0.21946463 | T17: -0.30194994 | U17: -0.22200191 | V17: -0.32784272 | W17: 2.7817757e+08 | X17: 3.1104852e+08 | Y17: 2.7908479e+08 | Z17: 3.230307e+08 | AA17: 63627727 | AB17: 336857.98 | AC17: -0.011079838 | AD17: 1204078.2 | AE17: -0.1039801 | AF17: 3876815.1 | AG17: -0.29429221 | AH17: 7076941.3 | AI17: 0.88771235 | AJ17: 34717.716 | AK17: -0.053033041 | AL17: 154994.76 | AM17: -0.13864321 | AN17: 409486.46 | AO17: 0.69589064 | AP17: 727104.26 | AQ17: 1.136299 | AR17: 22.821577 | AS17: 0.059879194 | AT17: -0.032878794 | AU17: -0.023661419 | AV17: -0.0048491903 | AW17: -0.18548287 | AX17: 23.597432 | AY17: 23.374654 | AZ17: 22.932782 | BA17: 28.018535 | BB17: 53376
A18: Curve | B18: CRV | C18: 2020-01-21 | D18: DeFi Exchange | E18: 1.51 | F18: 0.031770371 | G18: -0.52434273 | H18: -0.39502457 | I18: -0.35879181 | J18: 1.2646648 | K18: 54.01 | L18: 0.331577 | M18: 4.144826e+08 | N18: 5.5596233e+08 | O18: 4.9875758e+09 | P18: 0.075896073 | Q18: 7.403184e+09 | R18: -0.0013416949 | S18: -0.085294333 | T18: -0.039889286 | U18: 0.28729369 | V18: 0.84472921 | W18: 8.093515e+09 | X18: 7.7107607e+09 | Y18: 5.7509674e+09 | Z18: 4.0131549e+09 | AA18: 9.7784988e+10 | AB18: 1108240.2 | AC18: 0.032569006 | AD18: 3322010.5 | AE18: 0.25413549 | AF18: 8182842.1 | AG18: 0.75395698 | AH18: 12792839 | AI18: 0.76814518 | AJ18: 554120.1 | AK18: 0.032569006 | AL18: 1661005.3 | AM18: 0.25413549 | AN18: 4091421 | AO18: 0.75395698 | AP18: 6396419.5 | AQ18: 0.76814518 | AR18: 127.51384 | AS18: -0.058746272 | AT18: -0.36886322 | AU18: -0.54555614 | AV18: -0.61857088 | AW18: -0.56263498 | AX18: 202.03836 | AY18: 280.59316 | AZ18: 334.30547 | BA18: 291.55016 | BB18: 122191
A19: Decred | B19: DCR | C19: 2016-02-08 | D19: Blockchain | E19: 105.06 | F19: -0.086891214 | G19: -0.42535605 | H19: -0.43161548 | I19: -0.33300526 | J19: 3.6859578 | K19: 247.35 | L19: 0.43154 | M19: 67253221 | N19: 1.3480509e+09 | P19: 0.03479619 | AA19: 4.2830693e+10 | AB19: 2742.0688 | AC19: -0.01815047 | AD19: 9643.0947 | AE19: -0.15902308 | AF19: 30888.72 | AG19: 0.40227429 | AH19: 41179.697 | AI19: 10.846478 | AR19: 11872.951 | AS19: -0.25034989 | AT19: -0.34369278 | AU19: -0.37993151 | AV19: -0.36611818 | AW19: -0.45687775 | AX19: 18090.539 | AY19: 19147.806 | AZ19: 18730.544 | BA19: 21860.55 | BB19: 45456
A20: dHedge | B20: DHT | C20: 2020-06-17 | D20: Asset Management DeFi | E20: 1.5 | F20: -0.0093012808 | G20: -0.29658214 | H20: -0.46491466 | I20: -0.4342593 | J20: 0.056228075 | K20: 5.52 | L20: 0.362026 | M20: 7231375 | N20: 17667471 | O20: 150000000 | P20: 0.018434169 | Q20: 26336784 | R20: -0.06935999 | S20: -0.1845675 | T20: -0.20776668 | U20: -0.11440502 | V20: -0.10907279 | W20: 32297932 | X20: 33243721 | Y20: 29739084 | Z20: 29561095 | BB20: 12949
A21: DODO | B21: DODO | C21: 2020-09-29 | D21: DeFi Exchange | E21: 1.22 | F21: 0.094096417 | G21: -0.53784796 | H21: -0.56556705 | I21: -0.77121847 | J21: 4.0140378 | K21: 8.38 | L21: 0.150827 | M21: 48548361 | N21: 1.5226167e+08 | O21: 1220000000 | P21: 0.036902408 | Q21: 1.347494e+08 | R21: 0.02564295 | S21: -0.13726752 | T21: -0.087601658 | U21: 0.4956579 | V21: 1.5281012 | W21: 1.5618909e+08 | X21: 1.4768703e+08 | Y21: 90093731 | Z21: 53300635 | AA21: 2.3087494e+10 | AB21: 1041413 | AC21: 0.55997733 | AD21: 1886023.8 | AE21: 1.055678 | AF21: 4027999.4 | AG21: 0.35211803 | AH21: 6549262.2 | AI21: 1.5765489 | AR21: 54.939094 | AS21: -0.073984157 | AT21: -0.51588554 | AU21: -0.77786091 | AV21: -0.80839839 | AW21: -0.71593994 | AX21: 113.48369 | AY21: 247.31845 | AZ21: 286.73607 | BA21: 193.40661 | BB21: 90306
A22: Dogecoin | B22: DOGE | C22: 2013-12-06 | D22: Blockchain | E22: 0.315431 | F22: -0.061356408 | G22: -0.38788757 | H22: 0.26547014 | I22: 4.8923873 | J22: 74.937744 | K22: 0.731578 | L22: 8.69e-05 | M22: 9.267705e+09 | N22: 4.091817e+10 | P22: 0.26582503 | AA22: 1.1002158e+12 | AB22: 321966.94 | AC22: -0.12179911 | AD22: 2227325.1 | AE22: 1.7911317 | AF22: 3146366.2 | AG22: 8.5821264 | AH22: 3403753.9 | AI22: 314.85955 | AR22: 1560.2759 | AS22: -0.19484037 | AT22: -0.25639558 | AU22: -0.49241056 | AV22: -0.56195477 | AW22: -0.63311582 | AX22: 2098.2607 | AY22: 3073.8936 | AZ22: 3561.906 | BA22: 4252.7752 | BB22: 1603241
A23: dYdX | C23: 2018-10-03 | D23: DeFi Exchange | Q23: 1.5434433e+08 | R23: -0.083198466 | S23: -0.30801835 | T23: -0.39910633 | U23: -0.40140094 | V23: -0.15969739 | W23: 2.2304685e+08 | X23: 2.5685797e+08 | Y23: 2.5784258e+08 | Z23: 1.8367708e+08 | AA23: 2.5227557e+10 | AB23: 1809049.7 | AC23: 0.34979632 | AD23: 3875500.4 | AE23: 0.81087253 | AF23: 9093393.3 | AG23: -0.15117601 | AH23: 18751477 | AI23: 3.924737 | AJ23: 1219870.1 | AK23: 0.37846922 | AL23: 2530452.6 | AM23: 0.58765195 | AN23: 6866849.2 | AO23: -0.37255268 | AP23: 15294121 | AQ23: 2.8615752 | BB23: 32802
A24: Ellipsis Finance | B24: EPS | C24: 2021-03-14 | D24: DeFi Exchange | E24: 0.70363 | F24: 0.059463503 | G24: -0.56915356 | H24: -0.58094793 | M24: 8463764.6 | N24: 1.0725418e+08 | O24: 703630000 | P24: 0.016232588 | Q24: 2.0412473e+09 | R24: -0.0081651564 | S24: -0.09341896 | T24: -0.20147812 | U24: -0.138089 | V24: -0.138089 | W24: 2.2515883e+09 | X24: 2.5562822e+09 | Y24: 2.3682808e+09 | Z24: 2.3682808e+09 | BB24: 15795
A25: Enzyme Finance | B25: MLN | C25: 2016-08-01 | D25: Asset Management DeFi | E25: 51.9 | F25: 0.012734457 | G25: -0.43885231 | H25: -0.4717347 | I25: 0.30738822 | J25: 0.70602016 | K25: 258.26 | L25: 1.79 | M25: 7391175.3 | N25: 69500626 | O25: 94688280 | P25: 0.10427735 | Q25: 23791837 | R25: -0.093840758 | S25: -0.15278106 | T25: -0.22861998 | U25: -0.093109905 | V25: -0.093109905 | W25: 28082277 | X25: 30843212 | Y25: 26234532 | Z25: 26234532 | BB25: 24796
A26: Erasure Protocol | B26: NMR | C26: 2015-12-16 | D26: DeFi Prediction Market Other | E26: 39.34 | F26: 0.18173729 | G26: -0.45235277 | H26: -0.34950852 | I26: -0.037039996 | J26: 0.25660629 | K26: 93.15 | L26: 2.06 | M26: 47212451 | N26: 2.2331396e+08 | O26: 4.3274e+08 | P26: 0.069075643 | Q26: 11560534 | R26: -0.090464579 | S26: -0.25677592 | T26: -0.2901238 | U26: -0.23551271 | V26: -0.23551271 | W26: 15554574 | X26: 16285282 | Y26: 15121944 | Z26: 15121944 | BB26: 28786
A27: Ethereum | B27: ETH | C27: 2015-07-30 | D27: Blockchain | E27: 2172.58 | F27: -0.015817057 | G27: -0.39684146 | H27: -0.081062801 | I27: 0.21467154 | J27: 2.6049471 | K27: 4356.99 | L27: 0.432979 | M27: 8.2848852e+10 | N27: 2.5202372e+11 | P27: 0.28724055 | AA27: 7.5320165e+12 | AB27: 2.6457697e+08 | AC27: -0.0067517636 | AD27: 1.0873434e+09 | AE27: 0.38805768 | AF27: 2.499396e+09 | AG27: 0.60209976 | AH27: 3.497501e+09 | AI27: 17.488708 | AR27: 19.685367 | AS27: -0.19897399 | AT27: -0.3085844 | AU27: -0.47130799 | AV27: -0.33635569 | AW27: -0.54994722 | AX27: 28.471106 | AY27: 37.234093 | AZ27: 29.662527 | BA27: 43.74013 | BB27: 1252270
A28: Fei Protocol | B28: TRIBE | C28: 2021-03-21 | D28: Asset Management DeFi Stablecoin | E28: 0.914915 | F28: 0.013622166 | G28: -0.37997363 | H28: -0.31937081 | M28: 44828621 | N28: 3.6858927e+08 | O28: 914915000 | P28: 0.028888205 | Q28: 3.8278131e+08 | R28: -0.018637397 | S28: -0.091446898 | T28: -0.36985942 | U28: -0.49917154 | V28: -0.49917154 | W28: 4.2130868e+08 | X28: 6.0745384e+08 | Y28: 7.6429625e+08 | Z28: 7.6429625e+08 | BB28: 25394
A29: Filecoin | B29: FIL | C29: 2014-07-08 | D29: Blockchain | E29: 65.8 | F29: -0.066142647 | G29: -0.38974478 | H29: -0.52770965 | I29: 0.65839126 | J29: 1.2158756 | K29: 236.84 | L29: 20.06 | M29: 1.7433412e+09 | N29: 4.8366534e+09 | O29: 1.2989946e+11 | P29: 0.45210934 | AC29: -0.56540368 | AD29: 334294.66 | AE29: -0.8295473 | AF29: 2475078.8 | AG29: 1.6905949 | AH29: 2991649.6 | AI29: 1.5396011 | AR29: 33002.491 | AS29: 23.748042 | AT29: 31.426198 | AU29: 45.276292 | AV29: 28.548051 | AW29: 35.642219 | AX29: 1017.7724 | AY29: 713.16196 | AZ29: 1116.9093 | BA29: 900.66846 | BB29: 87927
A30: Futureswap | B30: FST | C30: 2020-04-15 | D30: DeFi Exchange | E30: 5.23 | F30: 0.050863623 | G30: -0.31825789 | H30: -0.31458302 | K30: 16.33 | L30: 4.29 | M30: 440785.28 | N30: 20876441 | O30: 5.23e+08 | P30: 0.0012624956 | Q30: 42525495 | R30: -0.023862986 | S30: -0.15841308 | T30: -0.24816505 | U30: -0.31815152 | V30: -0.31815152 | W30: 50530128 | X30: 56562275 | Y30: 62367954 | Z30: 62367954 | AA30: 1.5167721e+10 | AB30: 608657.84 | AC30: 0.08303341 | AD30: 1739093.5 | AE30: 0.10974289 | AF30: 3843647.5 | AG30: 0.50822131 | AH30: 5493800.4 | AR30: 25.541569 | AS30: -0.071100068 | AT30: -0.24914398 | AU30: -0.35489533 | AV30: -0.58152633 | AW30: -0.58152633 | AX30: 34.016601 | AY30: 39.592907 | AZ30: 61.035069 | BA30: 61.035069 | BB30: 6801
A31: Harvest Finance | B31: FARM | C31: 2020-08-16 | D31: Asset Management DeFi | E31: 69.69 | F31: 0.068024619 | G31: -0.44558315 | H31: -0.65531754 | I31: -0.74115543 | J31: -0.36775518 | K31: 5078.47 | L31: 54.3 | M31: 2319340.1 | N31: 38092621 | O31: 48115370 | P31: 0.035411489 | Q31: 3.3413992e+08 | R31: -0.052334766 | S31: -0.21429678 | T31: -0.34233349 | U31: -0.37951666 | V31: -0.39525181 | W31: 4.2527497e+08 | X31: 5.0806893e+08 | Y31: 5.3851553e+08 | Z31: 5.5252736e+08 | BB31: 48405
A32: Hegic | B32: HEGIC | C32: 2020-02-20 | D32: DeFi Insurance | E32: 0.114512 | F32: 0.18238786 | G32: -0.29988962 | H32: -0.18364552 | I32: -0.68547343 | J32: -0.57246389 | K32: 0.642093 | L32: 0.04329329 | M32: 3463344.4 | N32: 61526811 | O32: 3.4491128e+08 | P32: 0.015201286 | Q32: 41907366 | R32: -0.030116423 | S32: -0.17287003 | T32: -0.29658553 | U32: -0.32192885 | V32: -0.3736552 | W32: 50665998 | X32: 59577059 | Y32: 61803788 | Z32: 66907821 | AA32: 1.2313633e+09 | AB32: 4179611.2 | AC32: 0.66596569 | AD32: 8061176.5 | AE32: 0.8499193 | AF32: 14655855 | AG32: -0.00088297358 | AH32: 31553515 | AI32: 1.1595492 | AJ32: 677040.25 | AK32: 1.2679153 | AL32: 1045815.4 | AM32: 2.2350318 | AN32: 1650874.3 | AO32: 0.93834144 | AP32: 3293562 | AQ32: 0.66674398 | AR32: 3.6339403 | AS32: -0.021851615 | AT32: -0.3844207 | AU32: -0.60920675 | AV32: -0.73647581 | AW32: -0.73904734 | AX32: 5.9032855 | AY32: 9.2988822 | AZ32: 13.789779 | BA32: 13.925669 | BB32: 18183
A33: IDEX | B33: IDEX | C33: 2017-10-14 | D33: DeFi Exchange | E33: 0.04963644 | F33: 0.22492913 | G33: -0.45851685 | H33: -0.60473078 | I33: -0.19263601 | J33: 0.10809581 | K33: 0.409674 | L33: 0.00563813 | M33: 1630644 | N33: 27904488 | O33: 49636440 | P33: 0.045674633 | Q33: 15126439 | R33: -0.11952964 | S33: -0.29237538 | T33: -0.40457575 | U33: -0.39031909 | V33: -0.39031909 | W33: 21376360 | X33: 25404472 | Y33: 24810418 | Z33: 24810418 | AA33: 28863020 | AB33: 1268.9511 | AC33: -0.014330309 | AD33: 7354.1395 | AE33: -0.16673125 | AF33: 30020.034 | AG33: -0.68765368 | AH33: 87587.744 | AI33: -0.71599162 | AJ33: 1268.9511 | AK33: -0.014330309 | AL33: 7354.1395 | AM33: -0.16673125 | AN33: 30020.034 | AO33: -0.68765368 | AP33: 87587.744 | AQ33: -0.71599162 | AR33: 573.24146 | AS33: 0.086090686 | AT33: -0.23414562 | AU33: -0.59178855 | AV33: -0.40770997 | AW33: -0.011188537 | AX33: 748.49929 | AY33: 1404.2758 | AZ33: 967.83912 | BA33: 579.72777 | BB33: 51653
A34: Idle Finance | B34: IDLE | C34: 2019-04-23 | D34: Asset Management DeFi | E34: 7.62 | F34: -0.027948823 | G34: -0.47377656 | H34: -0.30443745 | I34: -0.49374094 | K34: 30.65 | L34: 0.789683 | M34: 237565 | N34: 13278511 | O34: 99060000 | P34: 0.0033205999 | Q34: 1.869269e+08 | R34: 0.056082317 | S34: -0.1375602 | T34: -0.057590079 | U34: 0.23577748 | V34: 0.61334308 | W34: 2.1674197e+08 | X34: 1.9834988e+08 | Y34: 1.5126259e+08 | Z34: 1.1586308e+08 | BB34: 9580
A35: Index Cooperative | B35: INDEX | C35: 2020-10-01 | D35: Asset Management DeFi | E35: 25.34 | F35: -0.012019348 | G35: -0.42255408 | H35: -0.28899483 | I35: 0.018584843 | J35: 2.8002944 | K35: 67.08 | L35: 1.33 | M35: 941017.91 | N35: 43576026 | O35: 253400000 | P35: 0.0029319652 | Q35: 1.9743554e+08 | R35: -0.089251946 | S35: -0.25839893 | T35: -0.21538229 | U35: 0.1373926 | V35: 0.58825213 | W35: 2.6622877e+08 | X35: 2.5163279e+08 | Y35: 1.735861e+08 | Z35: 1.2430995e+08
A36: Indexed Finance | B36: NDX | C36: 2021-04-23 | D36: Asset Management DeFi | E36: 2.75 | F36: 0.049961739 | G36: -0.50355577 | H36: -0.67448509 | I36: -0.71865341 | K36: 27.71 | L36: 1.01 | M36: 267255.91 | N36: 9480919.1 | O36: 27500000 | P36: 0.0034832028 | Q36: 21997039 | R36: -0.092012777 | S36: -0.25267037 | T36: -0.35611673 | U36: -0.34956521 | V36: -0.42337896 | W36: 29434186 | X36: 34163086 | Y36: 33818977 | Z36: 38148173 | BB36: 13338
A37: Instadapp | B37: INST | C37: 2018-10-16 | D37: DeFi Interoperability Other | Q37: 4125589150 | R37: -0.039239089 | S37: -0.11066065 | T37: 0.023244201 | U37: 0.64742543 | V37: 1.9910734 | W37: 4.6389369e+09 | X37: 4.0318715e+09 | Y37: 2.5042646e+09 | Z37: 1.3793005e+09
A38: Integral Protocol | B38: ITGR | C38: 2021-04-21 | D38: DeFi Exchange | Q38: 1.0623063e+08 | R38: -0.05205444 | S38: -0.38503563 | T38: -0.72194251 | U38: -0.74417062 | V38: -0.74417062 | W38: 1.7274274e+08 | X38: 3.8204556e+08 | Y38: 4.1524016e+08 | Z38: 4.1524016e+08 | BB38: 6176
A39: KeeperDAO | B39: ROOK | C39: 2020-07-18 | D39: Asset Management DeFi Other | E39: 189.63 | F39: 0.13782177 | G39: -0.52901631 | H39: -0.40115943 | I39: -0.59406614 | J39: 1.4540222 | K39: 838.98 | L39: 15.61 | M39: 6329241.9 | N39: 1.0715716e+08 | O39: 222682509 | P39: 0.022388573 | Q39: 68882776 | R39: -0.057151386 | S39: -0.23402098 | T39: -0.8186848 | U39: -0.80286384 | V39: -0.73284237 | W39: 89927758 | X39: 3.7990623e+08 | Y39: 3.4941726e+08 | Z39: 2.5783571e+08 | AA39: 5.7241077e+10 | AB39: 0.020925966 | AC39: -0.27641942 | AD39: 5517227.1 | AE39: -0.38249865 | AF39: 24656808 | AG39: -0.6261779 | AH39: 49098764 | AI39: 3.0113399 | AJ39: 0.020925966 | AK39: -0.27641942 | AL39: 5517227.1 | AM39: -0.38249865 | AN39: 24656808 | AO39: -0.6261779 | AP39: 49098764 | AQ39: 3.0113399 | AR39: 3.4279468 | AS39: -0.035143353 | AT39: -0.2430223 | AU39: -0.25160924 | AV39: -0.11941532 | AW39: -0.12764795 | AX39: 4.5284647 | AY39: 4.5804238 | AZ39: 3.8928077 | BA39: 3.9295452 | BB39: 20227
A40: Keep Network | B40: KEEP | C40: 2017-08-10 | D40: DeFi Interoperability | E40: 0.289022 | F40: 0.1393883 | G40: -0.37661515 | H40: -0.38537344 | I40: -0.2125421 | J40: -0.15272487 | K40: 6.1 | L40: 0.177138 | M40: 3289175.7 | N40: 1.2671757e+08 | O40: 289022000 | P40: 0.0053216886 | Q40: 1.883832e+08 | R40: -0.13411246 | S40: -0.3195512 | T40: -0.4502145 | U40: -0.43482732 | V40: -0.28948619 | W40: 2.768514e+08 | X40: 3.4264854e+08 | Y40: 3.3331973e+08 | Z40: 2.6513658e+08 | BB40: 18738
A41: Kusama | B41: KSM | C41: 2019-09-20 | D41: Blockchain | E41: 271.99 | F41: -0.11435447 | G41: -0.4999201 | H41: -0.18482781 | I41: -0.0074844112 | J41: 4.6666615 | K41: 621.71 | L41: 0.876572 | M41: 5.3130825e+08 | N41: 2.4272199e+09 | O41: 2719900000 | P41: 0.25215876 | AA41: 2.2692239e+10 | AB41: 1562.9455 | AC41: -0.2302149 | AD41: 44133.051 | AE41: -0.41110623 | AF41: 157900.09 | AG41: 1.2254192 | AH41: 190445.96 | AI41: 11.469742 | AJ41: 1250.3564 | AK41: -0.2302149 | AL41: 35306.441 | AM41: -0.41110623 | AN41: 126320.08 | AO41: 1.2254192 | AP41: 152356.77 | AQ41: 11.469742 | AR41: 5234.2904 | AS41: -0.15714176 | AT41: -0.28356392 | AU41: -0.030292513 | AV41: -0.14729381 | AW41: -0.27676114 | AX41: 7306.0117 | AY41: 5397.8034 | AZ41: 6138.4454 | BA41: 7237.2914 | BB41: 66965
A42: Kyber | B42: KNC | C42: 2018-02-10 | D42: DeFi Exchange | E42: 1.64 | F42: 0.080783986 | G42: -0.36704443 | H42: -0.33494379 | I42: -0.081869654 | J42: 0.43469226 | K42: 5.8 | L42: 0.116184 | M42: 1.1732814e+08 | N42: 1.4978618e+08 | O42: 370640000 | P42: 0.32362946 | Q42: 33665703 | R42: -0.062857595 | S42: -0.15302919 | T42: -0.28185382 | U42: 0.072747692 | V42: 0.63985076 | W42: 39748362 | X42: 46878621 | Y42: 31382685 | Z42: 20529736 | AA42: 3.8583319e+09 | AB42: 223691.49 | AC42: 0.097098493 | AD42: 655387.89 | AE42: 0.20377384 | AF42: 1941499.5 | AG42: -0.55987822 | AH42: 5615730.4 | AI42: 0.27621915 | AJ42: 167768.62 | AK42: 0.097098493 | AL42: 491540.92 | AM42: 0.20377384 | AN42: 1456124.7 | AO42: -0.55987822 | AP42: 4211797.8 | AQ42: 0.27621915 | AR42: 48.031119 | AS42: -0.042940778 | AT42: -0.27526965 | AU42: -0.52061312 | AV42: -0.40144311 | AW42: -0.063404326 | AX42: 66.274469 | AY42: 100.19281 | AZ42: 80.244868 | BA42: 51.282661 | BB42: 163252
A43: Lido Finance | B43: LDO | C43: 2020-04-21 | D43: Asset Management DeFi Other | E43: 2.18 | F43: 0.48753764 | G43: -0.32859018 | H43: 1.4761445 | I43: 0.75274138 | K43: 5.74 | L43: 0.505506 | M43: 5183281.8 | N43: 62945729 | O43: 2180000000 | P43: 0.0021208519 | Q43: 1.26852e+09 | R43: -0.041379077 | S43: -0.23430346 | T43: -0.24379681 | U43: 0.40554632 | V43: 0.85991062 | W43: 1.6566877e+09 | X43: 1.6774857e+09 | Y43: 9.0251028e+08 | Z43: 6.8203278e+08 | BB43: 23254
A44: Liquity | B44: LQTY | C44: 2020-04-21 | D44: DeFi Lending | E44: 9.94 | F44: 0.21589618 | G44: -0.36027786 | H44: -0.78693979 | K44: 146.94 | L44: 6.61 | M44: 1709355.5 | N44: 44822492 | O44: 994000000 | P44: 0.0020680631 | Q44: 2.0595547e+09 | R44: -0.033231974 | S44: -0.21786916 | T44: -0.3832039 | U44: -0.19041612 | V44: -0.19041612 | W44: 2.6332611e+09 | X44: 3.3391176e+09 | Y44: 2.543967e+09 | Z44: 2.543967e+09 | BB44: 15455
A45: Litecoin | B45: LTC | C45: 2011-10-07 | D45: Blockchain | E45: 152.78 | F45: -0.072821277 | G45: -0.48655065 | H45: -0.3652212 | I45: -0.26856666 | J45: 0.71549452 | K45: 410.26 | L45: 1.15 | M45: 9.0511541e+09 | N45: 1.0198504e+10 | P45: 0.76662639 | AA45: 1.8336929e+11 | AB45: 38607.447 | AC45: -0.066924302 | AD45: 204789.56 | AE45: 0.34709132 | AF45: 453366.29 | AG45: 1.1334183 | AH45: 651387.85 | AI45: 6.9664957 | AR45: 4229.5822 | AS45: -0.24913949 | AT45: -0.387167 | AU45: -0.51802701 | AV45: -0.57569056 | AW45: -0.65479429 | AX45: 6901.6881 | AY45: 8775.5586 | AZ45: 9968.1548 | BA45: 12252.353 | BB45: 672578
A46: Livepeer | B46: LPT | C46: 2017-03-25 | D46: Other | E46: 17.19 | F46: 0.20097443 | G46: -0.42150669 | H46: -0.37494946 | I46: 3.4889504 | J46: 12.072778 | K46: 45.44 | L46: 0.354051 | M46: 20352874 | N46: 3.9997752e+08 | O46: 4.0684383e+08 | P46: 0.026251749 | AB46: 3029.0105 | AC46: -0.032766962 | AD46: 19745.133 | AE46: 0.32454704 | AF46: 51436.028 | AG46: 0.33612901 | AH46: 78832.792 | AI46: 16.1121 | AJ46: 345.22611 | AK46: -0.07725585 | AL46: 3425.8535 | AM46: 0.10707481 | AN46: 10193.293 | AO46: 0.61597463 | AP46: 13740.727 | AQ46: 28.584753 | AR46: 1749.9937 | AS46: -0.017602385 | AT46: -0.28538672 | AU46: -0.44447218 | AV46: -0.32301018 | AW46: -0.018771928 | AX46: 2448.8682 | AY46: 3150.146 | AZ46: 2584.9631 | BA46: 1783.4729 | BB46: 11318
A47: Loopring | B47: LRC | C47: 2019-12-02 | D47: DeFi Exchange | E47: 0.294195 | F47: 0.032321689 | G47: -0.45035057 | H47: -0.35921901 | I47: -0.52898024 | J47: 0.36719571 | K47: 2.4 | L47: 0.01963893 | M47: 75492928 | N47: 3.6687151e+08 | O47: 4.0437512e+08 | P47: 0.20804105 | Q47: 1.5266698e+08 | R47: -0.053951005 | S47: -0.19835854 | T47: -0.28336469 | U47: -0.21569355 | V47: 0.093419881 | W47: 1.9044297e+08 | X47: 2.1303301e+08 | Y47: 1.946522e+08 | Z47: 1.3962338e+08 | AA47: 5.0774698e+09 | AB47: 290848.59 | AC47: -0.051501942 | AD47: 1078092.9 | AE47: 0.6020425 | AF47: 2433532.8 | AG47: 0.054713348 | AH47: 3518366.3 | AI47: 86.393327 | AJ47: 147441.72 | AK47: -0.045268956 | AL47: 563523.74 | AM47: 0.63871029 | AN47: 1260445.8 | AO47: 0.082080958 | AP47: 1859854.5 | AQ47: 75.134773 | AR47: 31.856427 | AS47: -0.031248906 | AT47: -0.25745535 | AU47: -0.5313243 | AV47: -0.65277614 | AW47: -0.94468673 | AX47: 42.901699 | AY47: 67.971152 | AZ47: 91.746079 | BA47: 575.92739 | BB47: 77507
A48: MakerDAO | B48: MKR | C48: 2017-12-18 | D48: DeFi Lending | E48: 3414.65 | F48: 0.42885163 | G48: -0.22330499 | H48: -0.1523148 | I48: 0.48669808 | J48: 4.8688688 | K48: 6292.31 | L48: 168.36 | M48: 1.0423507e+09 | N48: 3.0601277e+09 | O48: 3.4336935e+09 | P48: 0.13166548 | Q48: 8.6135708e+09 | R48: -0.051126505 | S48: -0.21224275 | T48: -0.26287564 | U48: -0.01690139 | V48: 0.34455723 | W48: 1.0934296e+10 | X48: 1.168537e+10 | Y48: 8.7616549e+09 | Z48: 6.4062508e+09 | AA48: 3.4941523e+09 | AB48: 3878000.3 | AC48: 0.054424975 | AD48: 13957074 | AE48: 0.38948016 | AF48: 31235488 | AG48: 2.0470842 | AH48: 39864204 | AI48: 4.2524286 | AJ48: 3877821.2 | AK48: 0.054428222 | AL48: 13956330 | AM48: 0.38948047 | AN48: 31234127 | AO48: 2.0469217 | AP48: 39862843 | AQ48: 4.2521485 | AR48: 20.894691 | AS48: 0.13397771 | AT48: -0.11824531 | AU48: -0.36416866 | AV48: -0.28533328 | AW48: -0.4029551 | AX48: 23.696717 | AY48: 32.862003 | AZ48: 29.236973 | BA48: 34.996851 | BB48: 151664
A49: MetaMask | C49: 2015-07-01 | D49: DeFi Exchange | AA49: 1.0859326e+10 | AB49: 769809.97 | AC49: -0.1013429 | AD49: 8070115.7 | AE49: 0.15902028 | AF49: 18353588 | AG49: 0.54213237 | AH49: 26600880 | AI49: 19.269691 | AJ49: 769809.97 | AK49: -0.1013429 | AL49: 8070115.7 | AM49: 0.15902028 | AN49: 18353588 | AO49: 0.54213237 | AP49: 26600880 | AQ49: 19.269691 | BB49: 192958
A50: Mirror Protocol | B50: MIR | C50: 2020-12-11 | D50: DeFi | E50: 4.07 | F50: 0.046276812 | G50: -0.45950373 | H50: -0.5269238 | I50: -0.29915021 | K50: 12.9 | L50: 0.898899 | M50: 1.1419632e+08 | N50: 2.7470417e+08 | O50: 1508240250 | P50: 0.032374606 | Q50: 7.8820634e+08 | R50: -0.15599179 | S50: -0.27032472 | T50: -0.32384902 | U50: -0.10491144 | V50: 0.50054945 | W50: 1.0802152e+09 | X50: 1.1657254e+09 | Y50: 8.8059034e+08 | Z50: 5.2527849e+08 | AA50: 1.9905056e+10 | AB50: 2008502.4 | AC50: 0.24296474 | AD50: 5071699.2 | AE50: 0.56761217 | AF50: 11232576 | AG50: 1.6351663 | AH50: 13601816 | AR50: 25.257239 | AS50: -0.1763848 | AT50: -0.42289416 | AU50: -0.66093205 | AV50: -0.68833677 | AW50: -0.76741056 | AX50: 43.765349 | AY50: 74.490198 | AZ50: 81.040163 | BA50: 108.59151 | BB50: 43349
A51: mStable | B51: MTA | C51: 2020-06-20 | D51: Asset Management DeFi Stablecoin | E51: 0.895332 | F51: 0.015175011 | G51: -0.48134257 | H51: -0.60754382 | I51: -0.64398424 | J51: -0.38232639 | K51: 11.03 | L51: 0.765136 | M51: 8812988.5 | N51: 25286462 | O51: 89533200 | P51: 0.081133369 | Q51: 61843792 | R51: -0.013056816 | S51: -0.055144421 | T51: -0.14803159 | U51: -0.011762122 | V51: 0.28810536 | W51: 65453169 | X51: 72589302 | Y51: 62579864 | Z51: 48011439 | BB51: 18300
A52: Nexus Mutual | B52: NXM | C52: 2019-05-30 | D52: DeFi Insurance | E52: 86.71 | F52: 0.083163934 | G52: -0.36464474 | H52: -0.042372438 | I52: 0.27053144 | J52: 2.3034738 | K52: 165.38 | L52: 6.96 | M52: 242247.36 | N52: 5.9951369e+08 | O52: 5.9951285e+08 | P52: 5.2575442e-06 | Q52: 3.8282809e+08 | R52: -0.047168262 | S52: -0.21023045 | T52: -0.24935892 | U52: 0.020646311 | V52: 0.39307742 | W52: 4.8473392e+08 | X52: 5.1000152e+08 | Y52: 3.7508399e+08 | Z52: 2.7480748e+08 | AA52: 3.19548e+09 | AC52: -0.091229678 | AD52: 1163287.1 | AE52: 0.34766586 | AF52: 2727785.8 | AG52: -0.71660448 | AH52: 7212551.1 | AI52: 16.79198 | AR52: 43.770391 | AS52: -0.078616201 | AT52: -0.19786011 | AU52: -0.36954862 | AV52: -0.12636982 | AW52: -0.61306939 | AX52: 54.567029 | AY52: 69.427068 | AZ52: 50.101739 | BA52: 113.12207 | BB52: 28217
A53: Notional Finance | C53: 2020-10-16 | D53: DeFi Exchange | Q53: 16561604 | R53: 0.0078659619 | S53: -0.071880766 | T53: -0.12775874 | U53: -0.095800391 | V53: -0.095800391 | W53: 17844263 | X53: 18987412 | Y53: 18316314 | Z53: 18316314 | BB53: 4033
A54: PancakeSwap | B54: CAKE | C54: 2020-09-14 | D54: DeFi Exchange | E54: 14.63 | F54: 0.18830061 | G54: -0.49772074 | H54: -0.45813788 | I54: -0.027263011 | J54: 44.293643 | M54: 8.0982975e+08 | N54: 2.5074767e+09 | P54: 0.40788135 | Q54: 6.637945e+09 | R54: -0.24249222 | S54: -0.29585174 | T54: -0.28694402 | U54: 0.0091297812 | V54: 0.09672054 | W54: 9.4269139e+09 | X54: 9.3091499e+09 | Y54: 6.5778903e+09 | Z54: 6.0525401e+09 | BB54: 772981
A55: Pangolin | B55: PNG | C55: 2020-04-23 | D55: DeFi Exchange | P55: 0.0019609203 | Q55: 3.5396838e+08 | R55: 0.019606993 | S55: 0.054152942 | T55: 0.20123885 | U55: 0.35293318 | V55: 0.35293318 | W55: 3.3578466e+08 | X55: 2.9466944e+08 | Y55: 2.6163035e+08 | Z55: 2.6163035e+08 | BB55: 18679
A56: Perpetual Protocol | B56: PERP | C56: 2020-09-06 | D56: DeFi Exchange | E56: 9.87 | F56: 0.13847332 | G56: 0.056959101 | H56: 0.51150248 | I56: 0.57264226 | J56: 8.0300392 | K56: 16.14 | L56: 0.669544 | M56: 45768968 | N56: 2.0894125e+08 | O56: 1480500000 | P56: 0.077141899 | AA56: 8.1718296e+10 | AB56: 3102444.2 | AC56: 0.34254212 | AD56: 6935655.8 | AE56: 1.761358 | AF56: 10920696 | AG56: 4.2540721 | AH56: 12950124 | AJ56: 3102444.2 | AK56: 0.34254212 | AL56: 6935655.8 | AM56: 1.761358 | AN56: 10920696 | AO56: 4.2540721 | AP56: 12950124 | AR56: 18.129662 | AS56: -0.053856677 | AT56: -0.18216301 | AU56: -0.35081158 | AV56: -0.60338942 | AW56: -0.75925075 | AX56: 22.167819 | AY56: 27.926657 | AZ56: 45.711494 | BA56: 75.305167 | BB56: 19477
A57: PieDAO | B57: DOUGH | C57: 2020-04-23 | D57: Asset Management DeFi | E57: 0.718428 | F57: 0.14261275 | G57: -0.35904607 | H57: -0.51396694 | I57: -0.44502123 | J57: -0.43724812 | K57: 6.27 | L57: 0.583214 | M57: 539490.48 | N57: 10952466 | O57: 71842800 | P57: 0.0080555497 | Q57: 14781979 | R57: -0.081285469 | S57: -0.24355835 | T57: -0.13294323 | U57: -0.16131458 | V57: -0.0022831478 | W57: 19541466 | X57: 17048455 | Y57: 17625177 | Z57: 14815805 | BB57: 12619
A58: Polkadot | B58: DOT | C58: 2020-08-20 | D58: Blockchain | E58: 18.89 | F58: -0.11290557 | G58: -0.55548347 | H58: -0.41657391 | I58: -0.50049985 | J58: 2.3062395 | K58: 49.35 | L58: 2.7 | M58: 4.586359e+09 | N58: 1.8755298e+10 | P58: 0.17086142 | AA58: 1.7250365e+11 | AB58: 30257.267 | AC58: -0.068875179 | AD58: 133801.87 | AE58: -0.073401916 | AF58: 397250.31 | AG58: 0.70832137 | AH58: 502030.09 | AI58: 28.972847 | AJ58: 24205.813 | AK58: -0.068875179 | AL58: 107041.49 | AM58: -0.073401916 | AN58: 317800.25 | AO58: 0.70832137 | AP58: 401624.07 | AQ58: 28.972847 | AR58: 11905.034 | AS58: -0.30365503 | AT58: -0.45190525 | AU58: -0.44614846 | AV58: -0.51321855 | AW58: -0.7378099 | AX58: 21720.758 | AY58: 21494.991 | AZ58: 24456.63 | BA58: 45406.114 | BB58: 431400
A59: Polymarket | C59: 2020-10-11 | D59: DeFi Prediction Market | AA59: 78066403 | AB59: 43330.374 | AC59: 0.092812322 | AD59: 133618.67 | AE59: -0.19241669 | AF59: 527420.28 | AG59: -0.5808771 | AH59: 1873815.6 | AI59: -0.72406032 | BB59: 8694
A60: PoolTogether | B60: POOL | C60: 2019-04-15 | D60: Asset Management DeFi Other | E60: 14.89 | F60: 0.17654942 | G60: -0.1234082 | H60: -0.14470464 | I60: -0.50295002 | K60: 53.98 | L60: 8.17 | M60: 1798635 | N60: 27325356 | O60: 148900000 | P60: 0.029022151 | Q60: 1.7935184e+08 | R60: -0.030326863 | S60: -0.11931609 | T60: -0.16844815 | U60: -0.096265635 | V60: -0.096265635 | W60: 2.0365064e+08 | X60: 2.1568329e+08 | Y60: 1.9845637e+08 | Z60: 1.9845637e+08 | AA60: 2.0211983e+08 | AB60: 83390.246 | AC60: -0.093159704 | AD60: 321498.29 | AE60: -0.48643411 | AF60: 1528282.3 | AG60: 3.1656316 | AH60: 1593203.2 | AI60: 36.534551 | AJ60: 41695.123 | AK60: -0.093159704 | AL60: 160749.14 | AM60: 0.094414458 | AN60: 299352.97 | AP60: 299352.97 | AR60: 39.335517 | AS60: -0.036837847 | AT60: -0.032896698 | AU60: 0.075613411 | AV60: -0.21883301 | AW60: -0.54614888 | AX60: 40.673542 | AY60: 36.570311 | AZ60: 50.354812 | BA60: 86.67053 | BB60: 21158
A61: PowerPool | B61: CVP | C61: 2020-04-23 | D61: Asset Management DeFi | E61: 0.981411 | F61: 0.0034753962 | G61: -0.53609499 | H61: -0.58661375 | I61: -0.66150142 | J61: -0.60880819 | K61: 17.27 | L61: 0.767227 | M61: 6063079.8 | N61: 14190338 | O61: 98141100 | P61: 0.051917598 | Q61: 18375566 | R61: -0.087700697 | S61: -0.21198242 | T61: -0.28096008 | U61: -0.30233556 | V61: -0.30233556 | W61: 23318726 | X61: 25555697 | Y61: 26338688 | Z61: 26338688 | BB61: 13071
A62: Rarible | B62: RARI | C62: 2020-09-19 | D62: DeFi NFT | E62: 11.89 | F62: 0.39602247 | G62: -0.25601208 | H62: -0.38725786 | I62: -0.27559236 | J62: 4.6398093 | K62: 46.7 | L62: 0.264878 | M62: 7708887.1 | N62: 46542850 | O62: 297250000 | P62: 0.024575519 | AA62: 3.060383e+08 | AB62: 290572.61 | AC62: -0.011933984 | AD62: 1299614.7 | AE62: -0.31476919 | AF62: 4809288.7 | AG62: 0.65365942 | AH62: 5998985.6 | AI62: 4.1686344 | AJ62: 290572.61 | AK62: -0.011933984 | AL62: 1299614.7 | AM62: -0.31476919 | AN62: 4809288.7 | AO62: 0.65365942 | AP62: 5998985.6 | AQ62: 4.1686344 | AR62: 19.425673 | AS62: 0.17704637 | AT62: -0.15310179 | AU62: -0.16805613 | AV62: -0.41669826 | AW62: -0.4065293 | AX62: 22.937436 | AY62: 23.34974 | AZ62: 33.302958 | BA62: 32.732321 | BB62: 156669
A63: Rari Capital | B63: RGT | C63: 2020-04-21 | D63: Asset Management DeFi | E63: 7.3 | F63: 0.61524408 | G63: -0.3075722 | H63: -0.58524764 | I63: -0.33641999 | J63: 9.3336824 | K63: 27.37 | L63: 0.213385 | M63: 4489928.7 | N63: 63703509 | O63: 73000000 | P63: 0.071471849 | Q63: 87013703 | T63: 0.0098124238 | U63: 0.83901177 | V63: 1.0665423 | W63: 87013703 | X63: 86168184 | Y63: 47315468 | Z63: 42105939 | BB63: 22803
A64: Reflexer | B64: FLX | C64: 2020-10-26 | D64: DeFi Lending Stablecoin | E64: 270.47 | F64: -0.017546471 | G64: -0.4655712 | H64: -0.63339838 | M64: 279458.04 | N64: 15570245 | O64: 270470000 | P64: 0.00077167753 | Q64: 1.0656847e+08 | R64: -0.066030238 | S64: -0.30396428 | T64: -0.57744643 | U64: -0.60694625 | V64: -0.60694625 | W64: 1.5310775e+08 | X64: 2.5220108e+08 | Y64: 2.711295e+08 | Z64: 2.711295e+08 | AA64: 77520536 | AB64: 23950.103 | AC64: -0.1118043 | AD64: 131678.73 | AE64: -0.28448454 | AF64: 508193.02 | AG64: 2.5071238 | AH64: 514706.05 | AJ64: 23950.103 | AK64: -0.1118043 | AL64: 131678.73 | AM64: -0.28448454 | AN64: 508193.02 | AO64: 2.5071238 | AP64: 514706.05 | AR64: 174.45053 | AS64: 0.0097200816 | AT64: -0.22828733 | AU64: -0.40673423 | AV64: -0.45528065 | AW64: -0.45528065 | AX64: 226.05633 | AY64: 294.05123 | AZ64: 320.25764 | BA64: 320.25764 | BB64: 10492
A65: Ren | B65: REN | C65: 2020-05-27 | D65: DeFi Interoperability | E65: 0.420022 | F65: 0.16310012 | G65: -0.43902787 | H65: -0.47041862 | I65: -0.65939715 | J65: 0.13660429 | K65: 1.8 | L65: 0.01548 | M65: 1.026451e+08 | N65: 3.6283687e+08 | O65: 420022000 | P65: 0.19297635 | Q65: 5.7556181e+08 | R65: -0.03301352 | S65: -0.13500035 | T65: -0.26953213 | U65: -0.28694138 | V65: -0.11011006 | W65: 6.6538965e+08 | X65: 7.8793583e+08 | Y65: 8.0717321e+08 | Z65: 6.4677865e+08 | AA65: 4.5601352e+09 | AB65: 21580.31 | AC65: -0.27663302 | AD65: 598687.51 | AE65: -0.53769199 | AF65: 2925497.5 | AG65: -0.53717206 | AH65: 5790066.2 | AI65: 0.74612822 | AR65: 59.585511 | AS65: 0.025829936 | AT65: -0.11143344 | AU65: -0.067954119 | AV65: -0.1629598 | AW65: -0.075666765 | AX65: 67.058017 | AY65: 63.929805 | AZ65: 71.185962 | BA65: 64.463236 | BB65: 79347
A66: Saddle Finance | C66: 2020-04-21 | D66: DeFi Exchange | Q66: 53223924 | R66: -0.009612686 | S66: -0.12359712 | T66: -0.3264028 | U66: -0.32229781 | V66: -0.32229781 | W66: 60729974 | X66: 79014468 | Y66: 78535860 | Z66: 78535860 | BB66: 5219
A67: Set Protocol | C67: 2017-10-01 | D67: Asset Management DeFi | Q67: 2.1257083e+08 | R67: -0.082570303 | S67: -0.24141321 | T67: -0.28200933 | U67: -0.20832632 | V67: -0.20832632 | W67: 2.8021953e+08 | X67: 2.960635e+08 | Y67: 2.6850815e+08 | Z67: 2.6850815e+08 | BB67: 29600
A68: SIREN Markets | B68: SI | C68: 2020-04-23 | D68: DeFi Exchange Insurance | E68: 1.14 | F68: -0.024850374 | G68: -0.44522483 | H68: -0.30906855 | M68: 563075.69 | N68: 12298784 | O68: 1.14e+08 | P68: 0.003541271 | Q68: 2801685.6 | R68: -0.060289504 | S68: -0.12368413 | T68: -0.32684652 | U68: -0.48650124 | V68: -0.48650124 | W68: 3197118.4 | X68: 4162031 | Y68: 5456070.9 | Z68: 5456070.9 | BB68: 3707
A69: Stake DAO | B69: SDT | C69: 2020-04-23 | D69: Asset Management DeFi | E69: 2.1 | F69: 0.20066504 | G69: -0.32287225 | H69: -0.62041922 | I69: -0.76947586 | K69: 17.38 | L69: 1.44 | M69: 802236.05 | N69: 21006197 | O69: 210000000 | P69: 0.00068550469 | Q69: 47617148 | R69: -0.018366547 | S69: -0.13896251 | T69: -0.39317666 | U69: -0.45704058 | V69: -0.45704058 | W69: 55302061 | X69: 78469539 | Y69: 87699276 | Z69: 87699276 | BB69: 9139
A70: Stellar | B70: XLM | C70: 2014-04-10 | D70: Blockchain | E70: 0.427444 | F70: 0.13632929 | G70: -0.40620536 | H70: -0.054602974 | I70: -0.086428889 | J70: 1.1986276 | K70: 0.875563 | L70: 0.00047612 | M70: 2.7589533e+09 | N70: 9.8771389e+09 | P70: 0.21314221 | AA70: 1.2822666e+11 | AB70: 901.43997 | AC70: 0.11845837 | AD70: 5147.9464 | AE70: 2.6315 | AF70: 8212.8859 | AG70: 0.13466694 | AH70: 17623.713 | AI70: 22.48935 | AR70: 162954.36 | AS70: -0.142044 | AT70: -0.33715653 | AU70: -0.61523638 | AV70: -0.61797266 | AW70: -0.58031583 | AX70: 245841.38 | AY70: 423518.1 | AZ70: 426551.56 | BA70: 388278.54 | BB70: 568789
A71: SushiSwap | B71: SUSHI | C71: 2020-09-09 | D71: DeFi Exchange | E71: 10.32 | F71: 0.15378928 | G71: -0.37164188 | H71: -0.085748725 | I71: -0.33883162 | J71: 7.0239719 | K71: 23.38 | L71: 0.475381 | M71: 2.038834e+09 | N71: 1.747792e+09 | O71: 2580000000 | P71: 0.49472036 | Q71: 3.4530006e+09 | R71: -0.1101015 | S71: -0.18647069 | T71: -0.2646804 | U71: -0.18625531 | V71: 0.14312202 | W71: 4.2444698e+09 | X71: 4.6959181e+09 | Y71: 4.2433464e+09 | Z71: 3.0206754e+09 | AA71: 2.7962928e+11 | AB71: 32633378 | AC71: 0.38316143 | AD71: 71248008 | AE71: 1.1121383 | AF71: 1.3710783e+08 | AG71: 0.70856607 | AH71: 2.1318555e+08 | AI71: 13.858763 | AJ71: 5438896.3 | AK71: 0.38316143 | AL71: 11874668 | AM71: 1.1121383 | AN71: 22851304 | AO71: 0.70856607 | AP71: 35530926 | AQ71: 13.858763 | AR71: 3.0755005 | AS71: -0.12258341 | AT71: -0.4091691 | AU71: -0.56709095 | AV71: -0.66526797 | AW71: -0.60784925 | AX71: 5.205382 | AY71: 7.1042648 | AZ71: 9.1879481 | BA71: 7.8426487 | BB71: 94726
A72: Swerve Finance | B72: SWRV | C72: 2020-04-22 | D72: DeFi Exchange | E72: 0.719216 | F72: 0.021117331 | G72: -0.55129706 | H72: -0.4607026 | I72: -0.43799007 | J72: 0.037682313 | K72: 39.04 | L72: 0.349328 | M72: 8025580.3 | N72: 8953122.4 | O72: 23734128 | P72: 0.3398905 | Q72: 18492705 | R72: -0.10079705 | S72: -0.23481909 | T72: -0.27015718 | U72: -0.079490079 | V72: -0.093460718 | W72: 24167756 | X72: 25337929 | Y72: 20089632 | Z72: 20399232 | BB72: 16595
A73: Synthetix | B73: SNX | C73: 2018-12-07 | D73: DeFi Exchange | E73: 13.19 | F73: 0.023068199 | G73: -0.32741601 | H73: -0.08757242 | I73: -0.32369836 | J73: 1.6341389 | K73: 28.53 | L73: 0.0347864 | M73: 2.988477e+08 | N73: 2.0356902e+09 | O73: 2.9860735e+09 | P73: 0.093158234 | Q73: 1.7859401e+09 | R73: -0.016584552 | S73: -0.13540607 | T73: -0.11833746 | U73: -0.19739266 | V73: -0.10717826 | W73: 2.0656403e+09 | X73: 2.0256504e+09 | Y73: 2.2251729e+09 | Z73: 2.0003322e+09 | AA73: 1.4407735e+10 | AB73: 1317991.2 | AC73: 0.31200899 | AD73: 3743666.7 | AE73: 1.4986123 | AF73: 7575811.4 | AG73: 0.15836147 | AH73: 17218787 | AI73: 4.9994987 | AJ73: 1317991.2 | AK73: 0.31200899 | AL73: 3743666.7 | AM73: 1.4986123 | AN73: 7575811.4 | AO73: 0.15836147 | AP73: 17218787 | AQ73: 4.9994987 | AR73: 67.744205 | AS73: -0.094458465 | AT73: -0.3479581 | AU73: -0.58860157 | AV73: -0.59948261 | AW73: -0.47126223 | AX73: 103.89548 | AY73: 164.66812 | AZ73: 169.14173 | BA73: 128.12439 | BB73: 129931
A74: Terra | B74: LUNA | C74: 2019-04-23 | D74: Blockchain | E74: 4.91 | F74: -0.19612178 | G74: -0.69853832 | H74: -0.65021564 | I74: -0.30290678 | J74: 10.945111 | K74: 22.36 | L74: 0.121798 | M74: 8.6531411e+08 | N74: 1.9036219e+09 | P74: 0.18433035 | AA74: 3.2659434e+10 | AB74: 132482.08 | AC74: -0.055541017 | AD74: 617796.31 | AE74: -0.073649785 | AF74: 1990838.4 | AG74: -0.22132393 | AH74: 4199972 | AI74: -0.41224527 | AR74: 261.70029 | AS74: -0.47731409 | AT74: -0.61643995 | AU74: -0.66991553 | AV74: -0.61850636 | AW74: -0.31736619 | AX74: 682.29287 | AY74: 792.82825 | AZ74: 685.98861 | BA74: 383.36849 | BB74: 75009
A75: Tezos | B75: XTZ | C75: 2018-09-16 | D75: Blockchain | E75: 3.12 | F75: -0.057275668 | G75: -0.45175677 | H75: -0.3528882 | I75: -0.27475795 | J75: 0.17319127 | K75: 8.27 | L75: 0.350476 | M75: 3.3081592e+08 | N75: 2.597074e+09 | P75: 0.13163442 | AA75: 2.7605566e+10 | AB75: 26290.397 | AC75: 0.19301179 | AD75: 83445.599 | AE75: 0.80610891 | AF75: 140425.38 | AG75: 6.805766 | AH75: 159764.12 | AI75: 18.505315 | AR75: 2643.3198 | AS75: -0.34321635 | AT75: -0.47316109 | AU75: -0.5575366 | AV75: -0.80829236 | AW75: -0.88961287 | AX75: 5017.3209 | AY75: 5974.0983 | AZ75: 13788.286 | BA75: 23945.906 | BB75: 117415
A76: Thorchain | B76: RUNE | C76: 2018-04-22 | D76: Interoperability | E76: 9.74 | F76: 0.28169673 | G76: -0.47151167 | H76: -0.22383849 | I76: 1.070324 | K76: 20.76 | L76: 1.55 | M76: 14731922 | N76: 1.5787035e+08 | O76: 1.7959374e+08 | P76: 0.029597194 | Q76: 3.0850523e+08 | R76: -0.1053758 | S76: -0.35083862 | T76: -0.45492408 | U76: -0.31833875 | V76: 0.092868705 | W76: 4.7523657e+08 | X76: 5.659858e+08 | Y76: 4.5257851e+08 | Z76: 2.8228938e+08 | BB76: 72844
A77: Tokenlon | B77: LON | C77: 2020-12-22 | D77: DeFi Exchange | E77: 2.75 | F77: 0.0090273587 | G77: -0.44923465 | H77: -0.47298622 | I77: -0.58342205 | K77: 9.81 | L77: 1.43 | M77: 30277932 | N77: 68315943 | O77: 550000000 | P77: 0.057960802 | AA77: 3.3092997e+10 | AB77: 2776683.3 | AC77: 0.19840827 | AD77: 8431914.2 | AE77: 1.2700819 | AF77: 16809584 | AG77: 0.30774102 | AH77: 34282437 | AI77: 2.6758066 | AJ77: 2776683.3 | AK77: 0.19840827 | AL77: 8431914.2 | AM77: 1.2700819 | AN77: 16809584 | AO77: 0.30774102 | AP77: 34282437 | AQ77: 2.6758066 | AR77: 5.5399435 | AS77: -0.049459428 | AT77: -0.34658695 | AU77: -0.67542571 | AV77: -0.75648017 | AW77: -0.69292119 | AX77: 8.4784709 | AY77: 17.068337 | AZ77: 22.749456 | BA77: 18.040787 | BB77: 8100
A78: UMA | B78: UMA | C78: 2020-04-11 | D78: DeFi Other | E78: 12.77 | F78: 0.048339999 | G78: -0.44241066 | H78: -0.4295136 | I78: -0.43660735 | J78: 0.47810942 | K78: 41.56 | L78: 0.303625 | M78: 41420308 | N78: 7.7242809e+08 | O78: 1.3094978e+09 | P78: 0.031234379 | Q78: 1.2081958e+08 | R78: -0.085645724 | S78: -0.2365457 | T78: -0.36479877 | U78: 0.032415113 | V78: 0.35864435 | W78: 1.5825385e+08 | X78: 1.9020678e+08 | Y78: 1.1702616e+08 | Z78: 88926568 | BB78: 38589
A79: Uniswap | B79: UNI | C79: 2018-11-02 | D79: DeFi Exchange | E79: 19.71 | F79: 0.12186475 | G79: -0.43441127 | H79: -0.37528074 | I79: -0.24654174 | J79: 4.0880137 | K79: 44.92 | L79: 1.03 | M79: 1.6401593e+09 | N79: 1.0247926e+10 | O79: 19710000000 | P79: 0.048046845 | Q79: 5.3238112e+09 | R79: -0.059764658 | S79: -0.20402356 | T79: -0.33029563 | U79: -0.17778207 | V79: 0.14803171 | W79: 6.688403e+09 | X79: 7.9494945e+09 | Y79: 6.4749394e+09 | Z79: 4.6373381e+09 | AA79: 8.6847739e+11 | AB79: 1.1906062e+08 | AC79: 0.35618889 | AD79: 2.8320111e+08 | AE79: 1.4503066 | AF79: 4.8588077e+08 | AG79: 2.1238168 | AH79: 6.651884e+08 | AI79: 7.782639 | AR79: 5.9109937 | AS79: -0.10583397 | AT79: -0.41110068 | AU79: -0.72163392 | AV79: -0.75771879 | AW79: -0.69169944 | AX79: 10.037359 | AY79: 21.234605 | AZ79: 24.397244 | BA79: 19.172828 | BB79: 504131
A80: Unit Protocol | B80: DUCK | C80: 2019-04-21 | D80: DeFi Lending Stablecoin | Q80: 3.3325459e+08 | R80: -0.10316737 | S80: -0.25184558 | T80: -0.23821438 | U80: 0.13658343 | V80: 0.28943708 | W80: 4.4543556e+08 | X80: 4.3746505e+08 | Y80: 2.9320732e+08 | Z80: 2.5844967e+08 | BB80: 5794
A81: Venus | B81: XVS | C81: 2020-09-14 | D81: DeFi Lending Stablecoin | E81: 30.63 | F81: 0.17741727 | G81: -0.73419537 | H81: -0.54368688 | I81: -0.59222431 | J81: 8.400313 | M81: 2.7858371e+08 | N81: 3.0741882e+08 | O81: 918900000 | P81: 0.29961061 | Q81: 2.1577804e+09 | R81: -0.077186777 | S81: -0.40751926 | T81: -0.60281402 | U81: -0.53051141 | V81: -0.53051141 | W81: 3.6419419e+09 | X81: 5.4326702e+09 | Y81: 4.5960231e+09 | Z81: 4.5960231e+09 | BB81: 105957
A82: Vesper Finance | B82: VSP | C82: 2020-04-22 | D82: Asset Management DeFi | E82: 14.52 | F82: 0.11809896 | G82: -0.3506662 | H82: -0.63590236 | I82: -0.47330853 | K82: 79.51 | L82: 9.99 | M82: 4264947.1 | N82: 49583140 | O82: 145200000 | P82: 0.025674224 | Q82: 8.6716158e+08 | R82: -0.026739358 | S82: -0.22712566 | T82: -0.35478235 | U82: -0.36499913 | V82: -0.36499913 | W82: 1.1219956e+09 | X82: 1.343983e+09 | Y82: 1.3656069e+09 | Z82: 1.3656069e+09 | BB82: 11885
A83: yearn.finance | B83: YFI | C83: 2020-07-17 | D83: Asset Management DeFi | E83: 38010 | F83: 0.17638334 | G83: -0.40959868 | H83: -0.082435827 | I83: 0.047045168 | J83: 0.61150115 | K83: 90787 | L83: 31.65 | M83: 1.0182927e+09 | N83: 1.3710308e+09 | O83: 1393674660 | P83: 0.6012431 | Q83: 3.4744138e+09 | R83: -0.017369218 | S83: -0.13685525 | T83: -0.062724758 | U83: 0.43530325 | V83: 1.1826167 | W83: 4.0252968e+09 | X83: 3.70693e+09 | Y83: 2.4206827e+09 | Z83: 1.591857e+09 | BB83: 121702
A84: Zcash | B84: ZEC | C84: 2016-10-28 | D84: Blockchain | E84: 133.09 | F84: -0.01542312 | G84: -0.49713644 | H84: -0.39392002 | I84: -0.085163712 | J84: 0.5358609 | K84: 3191.93 | L84: 19.75 | M84: 1.9719696e+09 | N84: 1.4775446e+09 | O84: 2794890000 | P84: 1.0712249 | AA84: 7.142311e+10 | AB84: 1672.3388 | AC84: -0.1329376 | AD84: 9199.4599 | AE84: 0.0034934967 | AF84: 22648.979 | AG84: 0.86296404 | AH84: 32120.689 | AI84: 4.0671074 | AR84: 25803.06 | AS84: 0.43748516 | AT84: 0.21301614 | AU84: 0.09152254 | AV84: 0.0030835199 | AW84: -0.1001978 | AX84: 21271.82 | AY84: 23639.512 | AZ84: 25723.741 | BA84: 28676.37 | BB84: 75713
